qv_session_manager/__init__.py
qv_session_manager/session_manager.py
qv_session_manager-0.3.0.dist-info/licenses/LICENSE
qv_session_manager-0.3.0.dist-info/METADATA
qv_session_manager-0.3.0.dist-info/WHEEL
qv_session_manager-0.3.0.dist-info/top_level.txt
qv_session_manager-0.3.0.dist-info/RECORD
