Metadata-Version: 2.4
Name: qv-session-manager
Version: 0.3.0
Summary: Simple, efficient session manager for persistent storage of conversations from qv-ollama-sdk in SQLite
Author-email: Thomas Bernhard <thomas@quantyverse.com>
Maintainer-email: Thomas Bernhard <thomas@quantyverse.com>
License: MIT
Project-URL: Homepage, https://quantyverse.ai
Project-URL: Documentation, https://github.com/quantyverse/qv-session-manager#readme
Project-URL: Repository, https://github.com/quantyverse/qv-session-manager.git
Project-URL: Issues, https://github.com/quantyverse/qv-session-manager/issues
Keywords: ollama,session-manager,conversation,sqlite,llm,chat,persistence
Classifier: Development Status :: 4 - Beta
Classifier: Intended Audience :: Developers
Classifier: License :: OSI Approved :: MIT License
Classifier: Operating System :: OS Independent
Classifier: Programming Language :: Python :: 3
Classifier: Programming Language :: Python :: 3.10
Classifier: Programming Language :: Python :: 3.11
Classifier: Programming Language :: Python :: 3.12
Classifier: Topic :: Software Development :: Libraries :: Python Modules
Classifier: Topic :: Database
Classifier: Topic :: Communications :: Chat
Classifier: Topic :: Scientific/Engineering :: Artificial Intelligence
Requires-Python: >=3.10
License-File: LICENSE
Requires-Dist: qv-ollama-sdk>=0.3.0
Provides-Extra: dev
Requires-Dist: pytest>=7.0; extra == "dev"
Requires-Dist: pytest-cov>=4.0; extra == "dev"
Requires-Dist: black>=23.0; extra == "dev"
Requires-Dist: flake8>=6.0; extra == "dev"
Requires-Dist: mypy>=1.0; extra == "dev"
Requires-Dist: pre-commit>=3.0; extra == "dev"
Provides-Extra: test
Requires-Dist: pytest>=7.0; extra == "test"
Requires-Dist: pytest-cov>=4.0; extra == "test"
Dynamic: license-file
